target_redcap/__init__.py
target_redcap/__main__.py
target_redcap/client.py
target_redcap/sinks.py
target_redcap/target.py
target_redcap/utils.py
target_redcap-0.0.4.dist-info/LICENSE
target_redcap-0.0.4.dist-info/METADATA
target_redcap-0.0.4.dist-info/WHEEL
target_redcap-0.0.4.dist-info/entry_points.txt
target_redcap-0.0.4.dist-info/RECORD
